{
  "id": "0107",
  "month": 1,
  "day": 7,
  "date_display": "January 7",
  "headline": "Steve Bullock Sworn In as 24th Governor of Montana, 2013",
  "year": 2013,
  "body": "On January 7, 2013, Steve Bullock was sworn in as the 24th Governor of Montana. A native of Missoula, Bullock had previously served as Montana's Attorney General. His political career has been marked by a focus on campaign finance reform, public education, and protecting Montana's natural resources. During his two terms as governor, which concluded on January 4, 2021, Bullock navigated the state through various challenges, including economic shifts and the initial phases of the COVID-19 pandemic. He was known for his bipartisan efforts and his commitment to expanding access to healthcare. Bullock also chaired the National Governors Association, demonstrating his leadership on a national level. His tenure saw significant legislative achievements and a continued emphasis on responsible governance for the state of Montana.",
  "category": "statehood",
  "location": "Helena, Lewis and Clark County",
  "latitude": 46.5921,
  "longitude": -112.0271,
  "tags": [
    "politics",
    "governor",
    "Montana history",
    "state government"
  ],
  "expandable": true,
  "sources": [
    "https://en.wikipedia.org/wiki/Steve_Bullock_(American_politician)",
    "https://www.nga.org/governor/steve-bullock/"
  ],
  "related_article": null
}