{
  "id": "0131",
  "month": 1,
  "day": 31,
  "date_display": "January 31",
  "headline": "Powell County Created in Montana, 1901",
  "year": 1901,
  "body": "Well now, gather 'round, and let ol' Twain spin ye a yarn about the way things were out West, particularly in that grand stretch of land they call Montana. It was the thirty-first day of January, in the year of our Lord nineteen hundred and one, when a stroke of the legislative pen brought forth a new entity into the world: Powell County. Not born of sweat and toil in the mines, mind you, nor sprung from the fertile soil of a ranch, but conjured up by lawmakers in Helena, who, I reckon, had a powerful thirst for order, or perhaps just a hankering to draw new lines on a map.\n\nThis new county, they said, was to be carved right out of the hide of Deer Lodge and Missoula counties. A bit like taking a slice from a pie, only this pie was vast and wild, full of mountains that scraped the sky and valleys where fortunes were dug from the earth. The county seat, they declared, would be Deer Lodge itself, a town that had seen its share of comings and goings, a veritable crossroads for folks with gold dust in their pockets and dreams in their eyes. It was a place where the stagecoach rattled in, bringing news and strangers, and where the cattle drives kicked up dust that settled on everything, including the hopes of men.\n\nNow, the creation of new counties back then was as common as a tall tale in a saloon. Montana was growing faster than a jackrabbit with a coyote on its tail, and with all that growth came a clamor for more local governance. Miners needed their claims sorted, ranchers needed their disputes settled, and everyone, from the humblest prospector to the grandest cattle baron, wanted a say in how their affairs were managed. The old county lines, drawn in a simpler time, were stretching thinner than a politician's promise. The industries, especially mining and ranching, were expanding like a prairie fire, and the need for law and order, or at least some semblance of it, became paramount.\n\nThey named this new county after Major John Wesley Powell, a man who, by all accounts, was more at home on a river than in a legislative chamber. An explorer and geologist, he'd led the first expedition down the mighty Colorado, a feat that would make even the most seasoned riverboat pilot tip his hat. It seems fitting, in a way, to name a county in such a rugged land after a man who understood the raw, untamed spirit of the West. His name, a testament to exploration and scientific endeavor, now graced a county born of the practical, often messy, business of state-building.\n\nThe establishment of Powell County, then, wasn't just a bureaucratic formality. It was another notch on the belt of Montana's administrative organization, a necessary step to bring government closer to the people, to facilitate local development, and to provide those essential services that keep a society from unraveling at the seams. It was a sign that Montana, having shed its territorial skin, was now fully committed to the grand, often bewildering, experiment of statehood. It was a time when the future was being hammered out, one county at a time, in the crucible of a rapidly changing frontier. As the legislative records of the time, specifically the Montana Laws of 1901, 7th legislative session, pages 101-106, would attest, the act was duly passed, bringing into being a new chapter for the residents of this corner of the Treasure State. The ink on the legislative act had barely dried, yet the work of building a community, of shaping a destiny, had already begun in earnest.",
  "category": "statehood",
  "location": "Deer Lodge, Powell County",
  "latitude": 46.3972,
  "longitude": -112.7319,
  "tags": [
    "county creation",
    "state government",
    "Montana history",
    "local governance"
  ],
  "expandable": true,
  "sources": [
    "https://en.wikipedia.org/wiki/Timeline_of_Montana_history",
    "https://en.wikipedia.org/wiki/Powell_County,_Montana"
  ],
  "related_article": null
}