{
  "id": "0409",
  "month": 4,
  "day": 9,
  "date_display": "April 9",
  "headline": "James Mitchell Ashley Appointed Montana Territorial Governor, 1869",
  "year": 1869,
  "body": "Well now, gather 'round, for I've a tale to spin about a peculiar sort of man who found himself dropped into the rough-and-tumble political arena of Montana Territory. His name was James Mitchell Ashley, and on April 9, 1869, President Ulysses S. Grant, bless his heart, saw fit to appoint this Ohio firebrand as the third Governor of our burgeoning domain. Ashley, a Radical Republican through and through, had cut his teeth in Washington, D.C., a staunch abolitionist who even penned the Thirteenth Amendment, freeing the slaves. He'd tangled with President Andrew Johnson himself, pushing for impeachment with the zeal of a revival preacher. But Montana, my friends, was a different beast entirely from the halls of Congress.\n\nHe arrived in Virginia City, then the territorial capital, a place still smelling of raw ambition and fresh-dug gold, where Democrats held sway like kings in their own dusty castles. Ashley, with his progressive notions, was about as welcome as a skunk at a garden party. He believed in things like public education for all, even for those industrious Chinese immigrants who were helping to lay the very tracks of progress across the land. Such ideas, you see, were considered radical, almost treasonous, by the good, conservative folk of Montana, who preferred their politics as unmixed as their whiskey.\n\nThe territorial legislature, a body as Democratic as a Southern drawl, took an immediate disliking to their new governor. They saw him as an outsider, a carpetbagger from the East, come to impose his high-minded ideals on their independent spirit. The clashes began almost immediately, a political wrestling match played out in the dusty streets and smoky saloons. Ashley, for his part, was no shrinking violet. He plunged into the fray, determined to bring what he saw as enlightened governance to the wild frontier.\n\nOne particular bone of contention, a matter that might seem trifling to some, was the infamous laundry tax. This was a levy that disproportionately affected the Chinese immigrants, who, with their tireless work ethic, often ran the territory's laundries. Ashley, with his deep-seated belief in equality, saw it for what it was: an oppressive measure. When the Sixth Session of the Legislative Assembly convened in late 1869, a body overwhelmingly Democratic, with barely a Republican to be found, Governor Ashley stood before them and, with characteristic bluntness, \"urged repeal of the laundry tax, calling it oppressive.\" One can almost hear the grumbling and shuffling of feet among the legislators, their faces set against this Eastern idealist.\n\nHis tenure, a mere fifteen months, was a constant battleground. His political appointments were met with scorn, his efforts to establish a robust public education system viewed with suspicion. He was a man out of time, perhaps, or simply in the wrong place for his particular brand of righteous politics. The local newspapers, largely Democratic, no doubt had a field day, painting him as a meddling busybody. By July 12, 1870, President Grant, perhaps weary of the constant squabbling, removed Ashley from his post. He left Montana, his grand plans largely unfulfilled, a testament to the stubborn independence of the territory and the unyielding nature of its political landscape. The dust settled, and Montana continued its march, but for a brief, tumultuous period, James Mitchell Ashley had tried to bend its will towards a more inclusive future, a task as difficult as trying to teach a grizzly bear to waltz.",
  "category": "statehood",
  "location": "Virginia City, Madison County",
  "latitude": 45.2938,
  "longitude": -111.9461,
  "tags": [
    "James Mitchell Ashley",
    "Territorial Governor",
    "Montana Politics",
    "Virginia City"
  ],
  "expandable": true,
  "sources": [
    "en.wikipedia.org/wiki/Timeline_of_Montana_history",
    "mths.mt.gov"
  ],
  "related_article": null
}