{
  "id": "0819",
  "month": 8,
  "day": 19,
  "date_display": "August 19",
  "headline": "Nez Perce Raid Howard's Camp at Camas Meadows, 1877",
  "year": 1877,
  "body": "The Nez Perce, a people dispossessed and driven from their ancestral lands, found themselves in the summer of 1877 engaged in a desperate flight for freedom. Having endured the brutal ambush at Big Hole, where women and children fell alongside warriors, their resolve hardened. General Oliver O. Howard, the one-armed soldier, pursued them relentlessly, his command a shadow upon their trail. Yet, the Nimiipuu, as they called themselves, were not merely fleeing; they were strategizing, observing, and preparing to strike back.\n\nOn the evening of August 19, 1877, Howard's weary troops established Camp Callaway in the Camas Meadows of Idaho Territory, just south of the Montana border. The general, wary of the elusive Nez Perce, had taken precautions, setting pickets to guard against surprise. But the eyes of the Nimiipuu scouts were keen, their knowledge of the land profound. They observed the soldier's camp, noting its defenses, and carried their intelligence back to the chiefs. A council was held, a plan forged not for direct confrontation, but for a swift, decisive raid to cripple the enemy's mobility. The objective was clear: to put Howard's cavalry on foot, to seize their horses and mules, thereby gaining precious time for their own beleaguered people.\n\nUnder the cloak of pre-dawn darkness, a small band of Nez Perce warriors, numbering at least twenty-eight, moved with practiced stealth. Among their leaders were the sagacious Looking Glass and the brave Ollokot, brother to Chief Joseph. Their movements were deliberate, each step measured to avoid detection. Yellow Wolf, a warrior present that night, recounted the meticulous planning and execution: \"We traveled slowly. No talking loud, no smoking. The match must not be seen. We went a good distance and then divided into two parties - one on each side of the creek... Before reaching the soldier camp, all stopped, and the leaders held council. How make the attack? The older men did this planning. Some wanted to leave the horses and enter the camp on foot. Chief Looking Glass and others thought the horses must not be left out. This last plan was chosen - to go mounted. Chief Joseph was not along.\" This careful deliberation underscored the gravity of their mission.\n\nAround four o'clock in the morning, the raid commenced. Some warriors dismounted, creeping silently among the picketed horses, their knives poised to cut the tethering ropes. Simultaneously, the mounted column approached the camp. A sudden, accidental gunshot from a foot scout named Otskai, coupled with a sentry's challenge, shattered the silence. The alarm was raised, but not before the Nez Perce had begun their work. Though many horses remained tethered, over two hundred mules were set free. The warriors, with shouts and skillful maneuvers, stampeded the animals northward, away from the startled soldiers. Bullets flew, striking wagons, but only one soldier sustained a minor wound in the initial chaos. The darkness, the unexpected assault, and the sheer audacity of the raid plunged the army camp into confusion. Cavalry officers and men scrambled to dress and mount, but the Nez Perce had already secured their prize.\n\nGeneral Howard, his camp now depleted of vital transport, ordered an immediate pursuit. Three companies of cavalry, approximately 150 horsemen, galloped northward at dawn, determined to recover the stolen stock. But the Nez Perce, ever resourceful, had anticipated this. A rear guard established an ambush eight miles north of Camp Callaway. Warriors deployed among the black lava hillocks, aspen trees, and sagebrush, some acting as decoys in a grassy meadow, while others crept forward to enfilade the pursuing troops. The ensuing skirmish, though not a large-scale battle, was fierce. Captain Randolph Norwood, with fifty men, found himself encircled, forced to establish defensive positions and fight for hours as the other two companies retreated. By mid-afternoon, Howard arrived with reinforcements, and the Nez Perce melted away, having achieved their objective. Norwood's company suffered one dead, two mortally wounded, and several others injured. The Nez Perce, according to Yellow Wolf, sustained only minor injuries. The raid, though it yielded mostly mules, severely hampered Howard's pursuit, buying the Nez Perce precious days in their arduous journey toward freedom. It was a testament to their resilience, their strategic acumen, and their unwavering spirit in the face of overwhelming odds.",
  "category": "native american history",
  "location": "Camas Meadows, Clark County, Idaho",
  "latitude": 44.35305555555556,
  "longitude": -111.885,
  "tags": [
    "native american history",
    "nez perce war",
    "military",
    "camas meadows",
    "chief joseph",
    "ollokot",
    "looking glass"
  ],
  "expandable": false,
  "sources": [
    "mths.mt.gov"
  ],
  "related_article": null
}