{
  "id": "0825",
  "month": 8,
  "day": 25,
  "date_display": "August 25",
  "headline": "Grant Kohrs Ranch National Historic Site authorized, 1972",
  "year": 1972,
  "body": "On August 25, 1972, U.S. President Richard Nixon signed legislation authorizing the establishment of the Grant-Kohrs Ranch National Historic Site in Deer Lodge, Montana. This act preserved one of the most significant 19th-century cattle ranches in the American West, recognizing its pivotal role in the development of the open-range cattle industry. The ranch, founded by Johnny Grant and later expanded by Conrad Kohrs, became known as the \"\"\"\"Home of the Montana Cowboy\"\"\"\" and played a crucial role in shaping the cattle industry from the 1860s to the early 20th century. The historic site now serves as a living museum, offering visitors a glimpse into the daily life and operations of a working cattle ranch during its heyday. It preserves original buildings, equipment, and livestock, providing educational programs that interpret the history of ranching, westward expansion, and the cultural heritage of the American cowboy. The site is a vital resource for understanding Montana\"\"\"\"s agricultural past and its enduring legacy.",
  "category": "agriculture",
  "location": "Deer Lodge, Powell County",
  "latitude": 46.398,
  "longitude": -112.7345,
  "tags": [
    "ranching",
    "agriculture",
    "history",
    "national historic site"
  ],
  "expandable": true,
  "sources": [
    "Wikipedia"
  ],
  "related_article": null
}