{
  "id": "1003",
  "month": 10,
  "day": 3,
  "date_display": "October 3",
  "headline": "Battle of Bear Paw Continues, 1877",
  "year": 1877,
  "body": "The wind bit sharp across the Bear Paw Mountains on October 3, 1877. It carried the acrid scent of gunpowder and the distant, chilling thud of cannon fire. For the Nez Perce, a people driven over a thousand miles from their ancestral Wallowa Valley, this was no mere skirmish; it was the grinding, desperate continuation of a flight for freedom. Colonel Nelson Miles, a man of relentless ambition, had ridden hard, covering 260 miles in nine days, to cut off Chief Joseph’s weary band, just thirty miles shy of the Canadian border. His command, some 450 strong, was bolstered by the grim, mechanical might of two Hotchkiss guns and a bronze 12-pounder cannon. These iron mouths roared, spitting fire and shell into the shallow ravines and coulees where Nez Perce families, their women and children, sought meager shelter. \n\nThe earth trembled with each concussion. Dust and rock fragments rained down. The Nez Perce, though outnumbered and starved, their bodies wracked by the ceaseless pursuit, fought with the ferocity of cornered animals. Every rifle shot, every arrow loosed, was a desperate prayer for survival. They had defended their homes, their hunting grounds, their very way of life across the Bitterroot Mountains, through the Yellowstone, and now, here, in the cold, unforgiving landscape of northern Montana. The soldiers pressed their advantage, their lines advancing, a relentless tide against a dwindling shore. The air was thick with the cries of the wounded, the shouts of men, and the guttural commands of officers. It was a brutal, intimate struggle, fought hand-to-hand in places, a testament to the sheer will of a people refusing to break. \n\nDays later, the spirit of resistance, though not extinguished, was forced to yield. Chief Joseph, seeing his people freezing, starving, and dying, would utter words that echoed the profound weariness of his soul: “I am tired of fighting. Our chiefs are killed. Looking-glass is dead. To be cold and have no blankets, the little children freezing to death. My people, some of them, have run away to the hills, and have no blankets, no food; no one knows where they are—perhaps freezing to death. I want to have time to look for my children, and see how many of them I can find. Maybe I shall find them among the dead. Hear me, my chiefs! I am tired; my heart is sick and sad. From where the sun now stands I will fight no more forever.” But on October 3rd, that decision still hung heavy in the cold Montana air, each cannon blast a hammer blow against the Nez Perce's fading hope.",
  "category": "native_history",
  "location": "Chinook, Blaine County",
  "latitude": 48.3779,
  "longitude": -109.2134,
  "tags": [
    "Nez Perce War",
    "Battle of Bear Paw",
    "Native American history",
    "military"
  ],
  "expandable": true,
  "sources": [
    "https://www.nps.gov/nepe/planyourvisit/bear-paw-battlefield.htm"
  ],
  "related_article": null
}