{
  "id": "1216",
  "month": 12,
  "day": 16,
  "date_display": "December 16",
  "headline": "William A. Clark, Copper King and Senator, Born, 1839",
  "year": 1839,
  "body": "Now, there are men, and then there are *men*. And then, far off in a category all his own, there was William Andrews Clark. Born on a December day in 1839, back in the quiet fields of Pennsylvania, young Clark wasn't content with the simple life. Oh no, not by a long shot. He had a gleam in his eye, a certain hunger that would eventually lead him west, to the rugged, untamed lands of Montana, where fortunes were made and lost faster than a gambler's last dollar. \n\nHe arrived in Montana, a territory brimming with the promise of copper, gold, and silver, and he set about making his mark with the zeal of a prospector striking a rich vein. He wasn't just digging for ore, mind you; he was digging for power, for influence, for a place among the titans. And titans he became, one of the fabled 'Copper Kings' who ruled over Butte, that rough-and-tumble city built on the back of mineral wealth. He dabbled in mining, banking, and railroads, each venture a stepping stone to an ever-greater empire. He built cities, or at least, he helped them sprout from the dust, places like Butte and Anaconda, where his will was as good as law. \n\nBut it wasn't enough, you see. A man like Clark, with his vast wealth and even vaster ambition, couldn't be content with mere riches. He craved the gilded halls of Washington, the prestige of a Senate seat. And so, he set his sights on the United States Senate, a pursuit that would become a tale for the ages, a scandal so rich and juicy it would make a seasoned politician blush. He tried once, and failed, but a man like Clark didn't take 'no' for an answer. He tried again, and this time, the whispers turned into shouts, the rumors into undeniable facts. It was said he bought his way into office, showering Montana legislators with money, a veritable rain of greenbacks. The Senate, bless its dignified heart, was not amused. They refused to seat him, a rare rebuke that would have sent a lesser man packing. \n\nBut Clark, he was no lesser man. He resigned, only to be appointed again by a sympathetic governor, and then, in a twist of fate that would make a novelist weep, he was elected by popular vote. The man simply would not be denied. He served his term, a controversial figure to the last, his name forever linked with the raw, unvarnished capitalism of the Gilded Age. \n\nIndeed, his reputation preceded him, even reaching the ears of a certain keen observer of human nature, a fellow by the name of Mark Twain. And Twain, never one to mince words, had this to say about our Copper King: \"He is as rotten a human being as can be found anywhere under the flag; he is a shame to the American nation.\" A harsh judgment, perhaps, but one that perfectly captures the sentiment of many who witnessed Clark's relentless pursuit of power. He was a force of nature, a man who shaped Montana's destiny, for better or for worse, leaving behind a legacy as complex and multifaceted as the copper veins he so eagerly exploited.",
  "category": "notable_birth",
  "location": "Deer Lodge, Powell County",
  "latitude": 46.3957,
  "longitude": -112.73,
  "tags": [
    "William A. Clark",
    "Copper King",
    "mining",
    "politics",
    "Montana history"
  ],
  "expandable": true,
  "sources": [
    "https://en.wikipedia.org/wiki/William_A._Clark",
    "https://www.whitehallledger.com/story/2022/12/14/community/this-month-in-montana-history-december/5854.html"
  ],
  "related_article": null
}