{
  "id": "1217",
  "month": 12,
  "day": 17,
  "date_display": "December 17",
  "headline": "Lewis and Clark Receive Crucial Maps at Fort Mandan, 1804",
  "year": 1804,
  "body": "On that frigid December 17th, 1804, a day when the very breath froze in the air and the Missouri River lay locked in an icy embrace, the captains of the Corps of Discovery, Meriwether Lewis and William Clark, found themselves at Fort Mandan, a temporary haven against the relentless northern winter. The thermometer, a marvel of scientific precision in that untamed land, plunged to a staggering forty-three degrees below zero, a testament to the raw, untamed power of nature they sought to comprehend. It was amidst this profound chill, a cold that bit to the bone and numbed the spirit, that a most unexpected and invaluable gift arrived, borne by the North West Company clerk, Hugh Heney.\n\nHeney, a man accustomed to the harsh realities of the fur trade, brought with him not pelts or provisions, but a treasure of far greater worth to the expedition: maps. These were not the finely engraved charts of European cartographers, but rather the accumulated wisdom of generations, drawn from the intimate knowledge of Native American tribes and the practical experience of seasoned traders. They depicted the intricate, serpentine course of the Missouri River, a watery highway stretching into the unknown heart of the continent, and hinted at the formidable mountain ranges that lay beyond, a barrier to the fabled Pacific.\n\nThe exchange was more than a mere transaction of paper; it was a profound confluence of cultures and knowledge, a moment where the scientific ambition of the young American republic met the ancient, living cartography of the indigenous peoples. These maps, crude yet profoundly accurate in their essential details, offered a glimpse into the vast, unmapped territories that would one day become Montana. They spoke of river bends, of significant tributaries, of the very lay of the land, information that would prove indispensable for the Corps of Discovery's arduous journey.\n\nClark, ever the meticulous cartographer, immediately set to work, integrating this new intelligence into his own evolving understanding of the continent. The information gleaned from Heney, and through him, from the Mandan and Hidatsa tribes, was a critical piece of the puzzle, illuminating the complex river systems and the geographical features that lay ahead. It was a stark reminder that in this wild, magnificent land, survival and success often hinged upon the willingness to learn from those who had walked its paths for centuries.\n\nThe winter at Fort Mandan, though a period of enforced inactivity by the elements, was far from idle. It was a season of crucial preparation, of intelligence gathering, and of forging relationships that would directly impact the expedition's ability to explore and map the Montana region. The maps received on that bitterly cold December day were not just lines on parchment; they were pathways to discovery, etched with the wisdom of the land itself. As Clark noted in his journal on December 17, 1804, after receiving the maps, \"We found Mr. Henny a verry intelligent man from the North West Company, who gave us much information.\"",
  "category": "exploration",
  "location": "Fort Mandan, North Dakota",
  "latitude": 47.2982,
  "longitude": -101.0876,
  "tags": [
    "Lewis and Clark Expedition",
    "Fort Mandan",
    "exploration",
    "Native American knowledge",
    "Missouri River"
  ],
  "expandable": true,
  "sources": [
    "https://lewis-clark.org/day-by-day/17-dec-1804/",
    "https://www.lewisandclark.travel/listing/fort-mandan/"
  ],
  "related_article": null
}